huang_ssh_demo/__init__.py
huang_ssh_demo-0.1.0.dist-info/WHEEL
huang_ssh_demo-0.1.0.dist-info/entry_points.txt
huang_ssh_demo-0.1.0.dist-info/METADATA
huang_ssh_demo-0.1.0.dist-info/RECORD
