Metadata-Version: 2.3
Name: huang-ssh-demo
Version: 0.1.0
Summary: Add your description here
Requires-Dist: mcp>=1.15.0
Requires-Dist: paramiko>=4.0.0
Requires-Python: >=3.13
